Workbook

Sheet 📊 Dashboard
B2: SMALL BUSINESS BOOKKEEPING
B5: Income · Expenses · Profit & Loss | 2025
C7: TOTAL INCOME | E7: TOTAL EXPENSES | G7: NET PROFIT | I7: PROFIT MARGIN
C8: =SUM('💰 Income'!G2:G1000) | E8: =SUM('💸 Expenses'!G2:G1000) | G8: =SUM('💰 Income'!G2:G1000)-SUM('💸 Expenses'!G2:G1000) | I8: =IF(SUM('💰 Income'!G2:G1000)=0,0,(SUM('💰 Income'!G2:G1000)-SUM('💸 Expenses'!G2:G1000))/SUM('💰 Income'!G2:G1000))
B10: MONTHLY SUMMARY
B11: MONTH | C11: INCOME | E11: EXPENSES | G11: NET | I11: MARGIN
B12: Jan | C12: =SUMPRODUCT((MONTH('💰 Income'!A2:A1000)=1)*('💰 Income'!G2:G1000)) | E12: =SUMPRODUCT((MONTH('💸 Expenses'!A2:A1000)=1)*('💸 Expenses'!G2:G1000)) | G12: =C12-E12 | I12: =IF(C12=0,0,(G12)/C12)
B13: Feb | C13: =SUMPRODUCT((MONTH('💰 Income'!A2:A1000)=2)*('💰 Income'!G2:G1000)) | E13: =SUMPRODUCT((MONTH('💸 Expenses'!A2:A1000)=2)*('💸 Expenses'!G2:G1000)) | G13: =C13-E13 | I13: =IF(C13=0,0,(G13)/C13)
B14: Mar | C14: =SUMPRODUCT((MONTH('💰 Income'!A2:A1000)=3)*('💰 Income'!G2:G1000)) | E14: =SUMPRODUCT((MONTH('💸 Expenses'!A2:A1000)=3)*('💸 Expenses'!G2:G1000)) | G14: =C14-E14 | I14: =IF(C14=0,0,(G14)/C14)
B15: Apr | C15: =SUMPRODUCT((MONTH('💰 Income'!A2:A1000)=4)*('💰 Income'!G2:G1000)) | E15: =SUMPRODUCT((MONTH('💸 Expenses'!A2:A1000)=4)*('💸 Expenses'!G2:G1000)) | G15: =C15-E15 | I15: =IF(C15=0,0,(G15)/C15)
B16: May | C16: =SUMPRODUCT((MONTH('💰 Income'!A2:A1000)=5)*('💰 Income'!G2:G1000)) | E16: =SUMPRODUCT((MONTH('💸 Expenses'!A2:A1000)=5)*('💸 Expenses'!G2:G1000)) | G16: =C16-E16 | I16: =IF(C16=0,0,(G16)/C16)
B17: Jun | C17: =SUMPRODUCT((MONTH('💰 Income'!A2:A1000)=6)*('💰 Income'!G2:G1000)) | E17: =SUMPRODUCT((MONTH('💸 Expenses'!A2:A1000)=6)*('💸 Expenses'!G2:G1000)) | G17: =C17-E17 | I17: =IF(C17=0,0,(G17)/C17)
B18: Jul | C18: =SUMPRODUCT((MONTH('💰 Income'!A2:A1000)=7)*('💰 Income'!G2:G1000)) | E18: =SUMPRODUCT((MONTH('💸 Expenses'!A2:A1000)=7)*('💸 Expenses'!G2:G1000)) | G18: =C18-E18 | I18: =IF(C18=0,0,(G18)/C18)
B19: Aug | C19: =SUMPRODUCT((MONTH('💰 Income'!A2:A1000)=8)*('💰 Income'!G2:G1000)) | E19: =SUMPRODUCT((MONTH('💸 Expenses'!A2:A1000)=8)*('💸 Expenses'!G2:G1000)) | G19: =C19-E19 | I19: =IF(C19=0,0,(G19)/C19)
B20: Sep | C20: =SUMPRODUCT((MONTH('💰 Income'!A2:A1000)=9)*('💰 Income'!G2:G1000)) | E20: =SUMPRODUCT((MONTH('💸 Expenses'!A2:A1000)=9)*('💸 Expenses'!G2:G1000)) | G20: =C20-E20 | I20: =IF(C20=0,0,(G20)/C20)
B21: Oct | C21: =SUMPRODUCT((MONTH('💰 Income'!A2:A1000)=10)*('💰 Income'!G2:G1000)) | E21: =SUMPRODUCT((MONTH('💸 Expenses'!A2:A1000)=10)*('💸 Expenses'!G2:G1000)) | G21: =C21-E21 | I21: =IF(C21=0,0,(G21)/C21)
B22: Nov | C22: =SUMPRODUCT((MONTH('💰 Income'!A2:A1000)=11)*('💰 Income'!G2:G1000)) | E22: =SUMPRODUCT((MONTH('💸 Expenses'!A2:A1000)=11)*('💸 Expenses'!G2:G1000)) | G22: =C22-E22 | I22: =IF(C22=0,0,(G22)/C22)
B23: Dec | C23: =SUMPRODUCT((MONTH('💰 Income'!A2:A1000)=12)*('💰 Income'!G2:G1000)) | E23: =SUMPRODUCT((MONTH('💸 Expenses'!A2:A1000)=12)*('💸 Expenses'!G2:G1000)) | G23: =C23-E23 | I23: =IF(C23=0,0,(G23)/C23)
B24: TOTAL | C24: =SUM('💰 Income'!G2:G1000) | E24: =SUM('💸 Expenses'!G2:G1000) | G24: =C24-E24 | I24: =IF(C24=0,0,G24/C24)

Sheet 💰 Income
A1: DATE | B1: CLIENT / CUSTOMER | C1: DESCRIPTION | D1: CATEGORY | E1: INVOICE # | F1: PAYMENT METHOD | G1: AMOUNT | H1: STATUS | I1: NOTES
A2: 2025-01-05 | B2: Acme Corp | C2: Web design project | D2: Design | E2: INV-001 | F2: Bank Transfer | G2: 2500 | H2: Paid
A3: 2025-01-18 | B3: Jane Smith | C3: Monthly retainer | D3: Consulting | E3: INV-002 | F3: PayPal | G3: 800 | H3: Paid
A4: 2025-02-03 | B4: Green Solutions | C4: Logo package | D4: Design | E4: INV-003 | F4: Credit Card | G4: 650 | H4: Paid
A5: 2025-02-20 | B5: TechStart Inc. | C5: SEO audit | D5: Marketing | E5: INV-004 | F5: Bank Transfer | G5: 1200 | H5: Paid
A6: 2025-03-10 | B6: Local Bakery | C6: Brand identity | D6: Design | E6: INV-005 | F6: Check | G6: 1800 | H6: Pending | I6: Follow-up needed
A7: 2025-03-28 | B7: Riverside LLC | C7: Social media management | D7: Marketing | E7: INV-006 | F7: Bank Transfer | G7: 950 | H7: Paid
A8: 2025-04-07 | B8: Global Events | C8: Event photography | D8: Photography | E8: INV-007 | F8: PayPal | G8: 1350 | H8: Paid
A9: 2025-04-22 | B9: Acme Corp | C9: Website maintenance | D9: Development | E9: INV-008 | F9: Bank Transfer | G9: 600 | H9: Paid | I9: Monthly
E10: TOTAL INCOME | G10: =SUM(G2:G9)

Sheet 💸 Expenses
A1: DATE | B1: VENDOR / PAYEE | C1: DESCRIPTION | D1: CATEGORY | E1: PAYMENT METHOD | F1: RECEIPT # | G1: AMOUNT | H1: TAX DEDUCTIBLE? | I1: NOTES
A2: 2025-01-03 | B2: Adobe Creative | C2: Monthly subscription | D2: Software | E2: Credit Card | F2: REC-001 | G2: 54.99 | H2: Yes
A3: 2025-01-10 | B3: Office Depot | C3: Desk supplies | D3: Office | E3: Credit Card | F3: REC-002 | G3: 87.32 | H3: Yes
A4: 2025-01-15 | B4: Zoom | C4: Pro plan | D4: Software | E4: Credit Card | F4: REC-003 | G4: 14.99 | H4: Yes
A5: 2025-02-01 | B5: Shopify | C5: Monthly plan | D5: Software | E5: Bank Transfer | F5: REC-004 | G5: 39 | H5: Yes
A6: 2025-02-14 | B6: Starbucks | C6: Client meeting | D6: Meals | E6: Credit Card | F6: REC-005 | G6: 23.75 | H6: Yes | I6: 50% deductible
A7: 2025-03-05 | B7: AT&T | C7: Business phone | D7: Utilities | E7: Bank Transfer | F7: REC-006 | G7: 85 | H7: Yes
A8: 2025-03-20 | B8: Canva Pro | C8: Annual subscription | D8: Software | E8: Credit Card | F8: REC-007 | G8: 119.99 | H8: Yes | I8: Annual
A9: 2025-04-02 | B9: Amazon | C9: Camera equipment | D9: Equipment | E9: Credit Card | F9: REC-008 | G9: 349 | H9: Yes
A10: 2025-04-18 | B10: Mailchimp | C10: Email marketing | D10: Marketing | E10: Credit Card | F10: REC-009 | G10: 30 | H10: Yes
E11: TOTAL EXPENSES | G11: =SUM(G2:G10)

Sheet 📈 Profit & Loss
B2: PROFIT & LOSS STATEMENT
B5: Fiscal Year 2025
B7: REVENUE
B8: Design | F8: =SUMIF('💰 Income'!D:D,"Design",'💰 Income'!G:G)
B9: Consulting | F9: =SUMIF('💰 Income'!D:D,"Consulting",'💰 Income'!G:G)
B10: Marketing | F10: =SUMIF('💰 Income'!D:D,"Marketing",'💰 Income'!G:G)
B11: Photography | F11: =SUMIF('💰 Income'!D:D,"Photography",'💰 Income'!G:G)
B12: Development | F12: =SUMIF('💰 Income'!D:D,"Development",'💰 Income'!G:G)
B13: Coaching | F13: =SUMIF('💰 Income'!D:D,"Coaching",'💰 Income'!G:G)
B14: Writing | F14: =SUMIF('💰 Income'!D:D,"Writing",'💰 Income'!G:G)
B15: Other | F15: =SUMIF('💰 Income'!D:D,"Other",'💰 Income'!G:G)
B16: TOTAL REVENUE | F16: =SUMIF('💰 Income'!H:H,"Paid",'💰 Income'!G:G)
B18: EXPENSES
B19: Software | F19: =SUMIF('💸 Expenses'!D:D,"Software",'💸 Expenses'!G:G)
B20: Office | F20: =SUMIF('💸 Expenses'!D:D,"Office",'💸 Expenses'!G:G)
B21: Meals | F21: =SUMIF('💸 Expenses'!D:D,"Meals",'💸 Expenses'!G:G)
B22: Utilities | F22: =SUMIF('💸 Expenses'!D:D,"Utilities",'💸 Expenses'!G:G)
B23: Equipment | F23: =SUMIF('💸 Expenses'!D:D,"Equipment",'💸 Expenses'!G:G)
B24: Marketing | F24: =SUMIF('💸 Expenses'!D:D,"Marketing",'💸 Expenses'!G:G)
B25: Travel | F25: =SUMIF('💸 Expenses'!D:D,"Travel",'💸 Expenses'!G:G)
B26: Contractor | F26: =SUMIF('💸 Expenses'!D:D,"Contractor",'💸 Expenses'!G:G)
B27: Insurance | F27: =SUMIF('💸 Expenses'!D:D,"Insurance",'💸 Expenses'!G:G)
B28: Rent | F28: =SUMIF('💸 Expenses'!D:D,"Rent",'💸 Expenses'!G:G)
B29: Other | F29: =SUMIF('💸 Expenses'!D:D,"Other",'💸 Expenses'!G:G)
B30: TOTAL EXPENSES | F30: =SUM('💸 Expenses'!G:G)
B32: NET PROFIT / LOSS
B33: Net Profit / Loss | F33: =SUM('💰 Income'!G:G)-SUM('💸 Expenses'!G:G)
B34: Profit Margin | F34: =IF(SUM('💰 Income'!G:G)=0,0,(SUM('💰 Income'!G:G)-SUM('💸 Expenses'!G:G))/SUM('💰 Income'!G:G))

Sheet 🏷️ Categories
B2: SPENDING BY CATEGORY
B4: CATEGORY | C4: INCOME | D4: EXPENSES | E4: NET | F4: % OF INCOME | G4: % OF EXPENSES
B5: Coaching | C5: =SUMIF('💰 Income'!D:D,"Coaching",'💰 Income'!G:G) | D5: =SUMIF('💸 Expenses'!D:D,"Coaching",'💸 Expenses'!G:G) | E5: =C5-D5 | F5: =IF(SUM('💰 Income'!G:G)=0,0,C5/SUM('💰 Income'!G:G)) | G5: =IF(SUM('💸 Expenses'!G:G)=0,0,D5/SUM('💸 Expenses'!G:G))
B6: Consulting | C6: =SUMIF('💰 Income'!D:D,"Consulting",'💰 Income'!G:G) | D6: =SUMIF('💸 Expenses'!D:D,"Consulting",'💸 Expenses'!G:G) | E6: =C6-D6 | F6: =IF(SUM('💰 Income'!G:G)=0,0,C6/SUM('💰 Income'!G:G)) | G6: =IF(SUM('💸 Expenses'!G:G)=0,0,D6/SUM('💸 Expenses'!G:G))
B7: Contractor | C7: =SUMIF('💰 Income'!D:D,"Contractor",'💰 Income'!G:G) | D7: =SUMIF('💸 Expenses'!D:D,"Contractor",'💸 Expenses'!G:G) | E7: =C7-D7 | F7: =IF(SUM('💰 Income'!G:G)=0,0,C7/SUM('💰 Income'!G:G)) | G7: =IF(SUM('💸 Expenses'!G:G)=0,0,D7/SUM('💸 Expenses'!G:G))
B8: Design | C8: =SUMIF('💰 Income'!D:D,"Design",'💰 Income'!G:G) | D8: =SUMIF('💸 Expenses'!D:D,"Design",'💸 Expenses'!G:G) | E8: =C8-D8 | F8: =IF(SUM('💰 Income'!G:G)=0,0,C8/SUM('💰 Income'!G:G)) | G8: =IF(SUM('💸 Expenses'!G:G)=0,0,D8/SUM('💸 Expenses'!G:G))
B9: Development | C9: =SUMIF('💰 Income'!D:D,"Development",'💰 Income'!G:G) | D9: =SUMIF('💸 Expenses'!D:D,"Development",'💸 Expenses'!G:G) | E9: =C9-D9 | F9: =IF(SUM('💰 Income'!G:G)=0,0,C9/SUM('💰 Income'!G:G)) | G9: =IF(SUM('💸 Expenses'!G:G)=0,0,D9/SUM('💸 Expenses'!G:G))
B10: Equipment | C10: =SUMIF('💰 Income'!D:D,"Equipment",'💰 Income'!G:G) | D10: =SUMIF('💸 Expenses'!D:D,"Equipment",'💸 Expenses'!G:G) | E10: =C10-D10 | F10: =IF(SUM('💰 Income'!G:G)=0,0,C10/SUM('💰 Income'!G:G)) | G10: =IF(SUM('💸 Expenses'!G:G)=0,0,D10/SUM('💸 Expenses'!G:G))
B11: Insurance | C11: =SUMIF('💰 Income'!D:D,"Insurance",'💰 Income'!G:G) | D11: =SUMIF('💸 Expenses'!D:D,"Insurance",'💸 Expenses'!G:G) | E11: =C11-D11 | F11: =IF(SUM('💰 Income'!G:G)=0,0,C11/SUM('💰 Income'!G:G)) | G11: =IF(SUM('💸 Expenses'!G:G)=0,0,D11/SUM('💸 Expenses'!G:G))
B12: Marketing | C12: =SUMIF('💰 Income'!D:D,"Marketing",'💰 Income'!G:G) | D12: =SUMIF('💸 Expenses'!D:D,"Marketing",'💸 Expenses'!G:G) | E12: =C12-D12 | F12: =IF(SUM('💰 Income'!G:G)=0,0,C12/SUM('💰 Income'!G:G)) | G12: =IF(SUM('💸 Expenses'!G:G)=0,0,D12/SUM('💸 Expenses'!G:G))
B13: Meals | C13: =SUMIF('💰 Income'!D:D,"Meals",'💰 Income'!G:G) | D13: =SUMIF('💸 Expenses'!D:D,"Meals",'💸 Expenses'!G:G) | E13: =C13-D13 | F13: =IF(SUM('💰 Income'!G:G)=0,0,C13/SUM('💰 Income'!G:G)) | G13: =IF(SUM('💸 Expenses'!G:G)=0,0,D13/SUM('💸 Expenses'!G:G))
B14: Office | C14: =SUMIF('💰 Income'!D:D,"Office",'💰 Income'!G:G) | D14: =SUMIF('💸 Expenses'!D:D,"Office",'💸 Expenses'!G:G) | E14: =C14-D14 | F14: =IF(SUM('💰 Income'!G:G)=0,0,C14/SUM('💰 Income'!G:G)) | G14: =IF(SUM('💸 Expenses'!G:G)=0,0,D14/SUM('💸 Expenses'!G:G))
B15: Other | C15: =SUMIF('💰 Income'!D:D,"Other",'💰 Income'!G:G) | D15: =SUMIF('💸 Expenses'!D:D,"Other",'💸 Expenses'!G:G) | E15: =C15-D15 | F15: =IF(SUM('💰 Income'!G:G)=0,0,C15/SUM('💰 Income'!G:G)) | G15: =IF(SUM('💸 Expenses'!G:G)=0,0,D15/SUM('💸 Expenses'!G:G))
B16: Photography | C16: =SUMIF('💰 Income'!D:D,"Photography",'💰 Income'!G:G) | D16: =SUMIF('💸 Expenses'!D:D,"Photography",'💸 Expenses'!G:G) | E16: =C16-D16 | F16: =IF(SUM('💰 Income'!G:G)=0,0,C16/SUM('💰 Income'!G:G)) | G16: =IF(SUM('💸 Expenses'!G:G)=0,0,D16/SUM('💸 Expenses'!G:G))
B17: Rent | C17: =SUMIF('💰 Income'!D:D,"Rent",'💰 Income'!G:G) | D17: =SUMIF('💸 Expenses'!D:D,"Rent",'💸 Expenses'!G:G) | E17: =C17-D17 | F17: =IF(SUM('💰 Income'!G:G)=0,0,C17/SUM('💰 Income'!G:G)) | G17: =IF(SUM('💸 Expenses'!G:G)=0,0,D17/SUM('💸 Expenses'!G:G))
B18: Software | C18: =SUMIF('💰 Income'!D:D,"Software",'💰 Income'!G:G) | D18: =SUMIF('💸 Expenses'!D:D,"Software",'💸 Expenses'!G:G) | E18: =C18-D18 | F18: =IF(SUM('💰 Income'!G:G)=0,0,C18/SUM('💰 Income'!G:G)) | G18: =IF(SUM('💸 Expenses'!G:G)=0,0,D18/SUM('💸 Expenses'!G:G))
B19: Travel | C19: =SUMIF('💰 Income'!D:D,"Travel",'💰 Income'!G:G) | D19: =SUMIF('💸 Expenses'!D:D,"Travel",'💸 Expenses'!G:G) | E19: =C19-D19 | F19: =IF(SUM('💰 Income'!G:G)=0,0,C19/SUM('💰 Income'!G:G)) | G19: =IF(SUM('💸 Expenses'!G:G)=0,0,D19/SUM('💸 Expenses'!G:G))
B20: Utilities | C20: =SUMIF('💰 Income'!D:D,"Utilities",'💰 Income'!G:G) | D20: =SUMIF('💸 Expenses'!D:D,"Utilities",'💸 Expenses'!G:G) | E20: =C20-D20 | F20: =IF(SUM('💰 Income'!G:G)=0,0,C20/SUM('💰 Income'!G:G)) | G20: =IF(SUM('💸 Expenses'!G:G)=0,0,D20/SUM('💸 Expenses'!G:G))
B21: Writing | C21: =SUMIF('💰 Income'!D:D,"Writing",'💰 Income'!G:G) | D21: =SUMIF('💸 Expenses'!D:D,"Writing",'💸 Expenses'!G:G) | E21: =C21-D21 | F21: =IF(SUM('💰 Income'!G:G)=0,0,C21/SUM('💰 Income'!G:G)) | G21: =IF(SUM('💸 Expenses'!G:G)=0,0,D21/SUM('💸 Expenses'!G:G))
